drjson/drjson.cpython-310-darwin.so
drjson/__init__.py
drjson/drjson.pyi
drjson/py.typed
drjson-3.3.0.dist-info/RECORD
drjson-3.3.0.dist-info/WHEEL
drjson-3.3.0.dist-info/top_level.txt
drjson-3.3.0.dist-info/METADATA
